[{"Founder(s)":"Travis Kalanick, Garrett Camp","Company Name":"Uber","Industry":"Transportation Services","Last Reported/Projected Revenue":"$2 billion","Latest Valuation":"$62 billion","Location":"San Francisco, CA","Founded":"2009"},{"Founder(s)":"Hong Feng, Lei Jun, Zhou Guangping, Li Wangqiang, Huang Jiangji, Lin Bin","Company Name":"Xiaomi","Industry":"Consumer Electronics","Last Reported/Projected Revenue":"$20 billion","Latest Valuation":"$46 billion","Location":"Beijing, China","Founded":"2010"},{"Founder(s)":"Brian Chesky, Joe Gebbia, Nathan Blecharczyk, Laurence Tosi","Company Name":"Airbnb","Industry":"Lodging Services","Last Reported/Projected Revenue":"$900 million","Latest Valuation":"$25.5 billion","Location":"San Francisco, CA","Founded":"2008"},{"Founder(s)":"Nathan Gettings, Peter Thiel, Alex Karp, Joe Lonsdale, Stephen Cohen","Company Name":"Palantir","Industry":"Data Analytics Software","Last Reported/Projected Revenue":"$450 million","Latest Valuation":"$20.5 billion","Location":"Palo Alto, CA","Founded":"2004"},{"Founder(s)":"Cheng Wei, Zhang Bo","Company Name":"Didi Chuxing","Industry":"Transportation Services","Last Reported/Projected Revenue":"$185 million","Latest Valuation":"$16 billion","Location":"Beiing, China","Founded":"2012"},{"Founder(s)":"Evan Spiegel, Bobby Murphy","Company Name":"Snapchat","Industry":"Social Media","Last Reported/Projected Revenue":"$100 million","Latest Valuation":"$16 billion","Location":"Venice, CA","Founded":"2011"},{"Founder(s)":"","Company Name":"China Internet Plus","Industry":"Internet Services","Last Reported/Projected Revenue":"N/A","Latest Valuation":"$15 billion","Location":"","Founded":""},{"Founder(s)":"","Company Name":"Flipkart","Industry":"E-commerce","Last Reported/Projected Revenue":"$1 billion","Latest Valuation":"$15 billion","Location":"","Founded":""},{"Founder(s)":"","Company Name":"SpaceX","Industry":"Aerospace","Last Reported/Projected Revenue":"$634 - $831 million","Latest Valuation":"$12 billion","Location":"","Founded":""},{"Founder(s)":"","Company Name":"Pinterest","Industry":"Social Media","Last Reported/Projected Revenue":"$169 million","Latest Valuation":"$11 billion","Location":"","Founded":""},{"Founder(s)":"","Company Name":"Dropbox","Industry":"Cloud Storage","Last Reported/Projected Revenue":"$216 million","Latest Valuation":"$10 billion","Location":"","Founded":""},{"Founder(s)":"","Company Name":"Lufax","Industry":"Financial Services","Last Reported/Projected Revenue":"$706 million","Latest Valuation":"$10 billion","Location":"","Founded":""},{"Founder(s)":"","Company Name":"WeWork","Industry":"Coworking","Last Reported/Projected Revenue":"$74.6 million","Latest Valuation":"$10 billion","Location":"","Founded":""},{"Founder(s)":"","Company Name":"Spotify","Industry":"Streaming Media","Last Reported/Projected Revenue":"$1.22 billion","Latest Valuation":"$8.5 Billion","Location":"","Founded":""},{"Founder(s)":"","Company Name":"DJI","Industry":"Robotics","Last Reported/Projected Revenue":"$1 billion","Latest Valuation":"$8 billion","Location":"","Founded":""},{"Founder(s)":"","Company Name":"Zhong An","Industry":"Insurance","Last Reported/Projected Revenue":"$441.96 million","Latest Valuation":"$8 billion","Location":"","Founded":""},{"Founder(s)":"","Company Name":"Intarcia Therapeutics","Industry":"Biotechnology","Last Reported/Projected Revenue":"N/A","Latest Valuation":"$5.5 billion","Location":"","Founded":""},{"Founder(s)":"","Company Name":"Lyft","Industry":"Transportation Services","Last Reported/Projected Revenue":"$1 billion","Latest Valuation":"$5.5 billion","Location":"","Founded":""},{"Founder(s)":"","Company Name":"Coupang","Industry":"E-commerce","Last Reported/Projected Revenue":"N/A","Latest Valuation":"$5 billion","Location":"","Founded":""},{"Founder(s)":"","Company Name":"Ola","Industry":"Transportation Services","Last Reported/Projected Revenue":"$1 billion","Latest Valuation":"$5 billion","Location":"","Founded":""},{"Founder(s)":"","Company Name":"Snapdeal","Industry":"E-commerce","Last Reported/Projected Revenue":"$138.6 million","Latest Valuation":"$5 billion","Location":"","Founded":""},{"Founder(s)":"","Company Name":"Stemcentrx","Industry":"Cancer Treatments","Last Reported/Projected Revenue":"$27 million","Latest Valuation":"$5 billion","Location":"","Founded":""},{"Founder(s)":"","Company Name":"Stripe","Industry":"Mobile Payments","Last Reported/Projected Revenue":"$450 million","Latest Valuation":"$5 billion","Location":"","Founded":""},{"Founder(s)":"","Company Name":"Zenefits","Industry":"Business Software","Last Reported/Projected Revenue":"$60 million","Latest Valuation":"$4.5 billion","Location":"","Founded":""},{"Founder(s)":"","Company Name":"Social Finance","Industry":"Financial Services","Last Reported/Projected Revenue":"$40 million","Latest Valuation":"$4 billion","Location":"","Founded":""},{"Founder(s)":"","Company Name":"Vice Media","Industry":"Media & Entertainment","Last Reported/Projected Revenue":"$1 billion","Latest Valuation":"$4 billion","Location":"","Founded":""},{"Founder(s)":"","Company Name":"Tanium","Industry":"Business Software","Last Reported/Projected Revenue":"$200 million","Latest Valuation":"$3.7 billion","Location":"","Founded":""},{"Founder(s)":"","Company Name":"UCar","Industry":"Transportation Services","Last Reported/Projected Revenue":"N/A","Latest Valuation":"$3.6 billion","Location":"","Founded":""},{"Founder(s)":"","Company Name":"Credit Karma","Industry":"Financial Software","Last Reported/Projected Revenue":"$200 million","Latest Valuation":"$3.5 billion","Location":"","Founded":""},{"Founder(s)":"","Company Name":"Global Fashion Group","Industry":"E-commerce","Last Reported/Projected Revenue":"$1.047 billion","Latest Valuation":"$3.4 billion","Location":"","Founded":""},{"Founder(s)":"","Company Name":"Jawbone","Industry":"Consumer Electronics","Last Reported/Projected Revenue":"$600 million","Latest Valuation":"$3.3 billion","Location":"","Founded":""},{"Founder(s)":"","Company Name":"Meizu","Industry":"Consumer Electronics","Last Reported/Projected Revenue":"$451.5 million","Latest Valuation":"$3.3 billion","Location":"","Founded":""},{"Founder(s)":"","Company Name":"CloudFlare","Industry":"Web Publishing","Last Reported/Projected Revenue":"$100 million","Latest Valuation":"$3.2 billion","Location":"","Founded":""},{"Founder(s)":"","Company Name":"Delivery Hero","Industry":"Food Delivery","Last Reported/Projected Revenue":"$33 million","Latest Valuation":"$3.1 billion","Location":"","Founded":""},{"Founder(s)":"","Company Name":"Machine Zone","Industry":"Video Games","Last Reported/Projected Revenue":"$600 million","Latest Valuation":"$3.1 billion","Location":"","Founded":""},{"Founder(s)":"","Company Name":"Bloom Energy","Industry":"Alternative Energy","Last Reported/Projected Revenue":"N/A","Latest Valuation":"$3 billion","Location":"","Founded":""},{"Founder(s)":"","Company Name":"DocuSign","Industry":"Business Software","Last Reported/Projected Revenue":"$100 million","Latest Valuation":"$3 billion","Location":"","Founded":""},{"Founder(s)":"","Company Name":"Ele.me","Industry":"Food Delivery","Last Reported/Projected Revenue":"$1.5 million?","Latest Valuation":"$3 billion","Location":"","Founded":""},{"Founder(s)":"","Company Name":"Fanatics","Industry":"E-commerce","Last Reported/Projected Revenue":"$1 billion","Latest Valuation":"$3 billion","Location":"","Founded":""},{"Founder(s)":"","Company Name":"Legendary Entertainment","Industry":"Film","Last Reported/Projected Revenue":"$152 million","Latest Valuation":"$3 billion","Location":"","Founded":""}]